wootrade/__init__.py
wootrade/authentication.py
wootrade/client.py
wootrade/enums.py
wootrade/exceptions.py
wootrade/streams.py
wootrade/threaded_stream.py
python_wootrade-0.1.8.dist-info/LICENSE
python_wootrade-0.1.8.dist-info/METADATA
python_wootrade-0.1.8.dist-info/WHEEL
python_wootrade-0.1.8.dist-info/top_level.txt
python_wootrade-0.1.8.dist-info/zip-safe
python_wootrade-0.1.8.dist-info/RECORD
