Metadata-Version: 2.1
Name: python-wootrade
Version: 0.1.8
Summary: Wootrade python API
Home-page: https://github.com/wanth1997/python-wootrade
Author: tinghsuwan
Author-email: wanth1997@gmail.com
License: MIT
Platform: UNKNOWN
Classifier: Programming Language :: Python :: 3
Classifier: License :: OSI Approved :: MIT License
Classifier: Operating System :: OS Independent
Requires-Dist: requests
Requires-Dist: aiohttp
Requires-Dist: websockets
